pycanum/__init__.py
pycanum/httpdata.py
pycanum/main.py
pycanum/pthreadVC2.dll
pycanum/pycanum.py
pycanum/sysamhttp.exe
pycanum-5.0.1.dist-info/LICENCE.txt
pycanum-5.0.1.dist-info/METADATA
pycanum-5.0.1.dist-info/WHEEL
pycanum-5.0.1.dist-info/top_level.txt
pycanum-5.0.1.dist-info/RECORD
